gidapptools/__init__.py
gidapptools/__main__.py
gidapptools/cli_info.py
gidapptools/custom_types.py
gidapptools/errors.py
gidapptools/abstract_classes/__init__.py
gidapptools/abstract_classes/abstract_meta_factory.py
gidapptools/abstract_classes/abstract_meta_item.py
gidapptools/code_generation/__init__.py
gidapptools/code_generation/python.py
gidapptools/data/__init__.py
gidapptools/data/conversion_data.py
gidapptools/data/general_data.py
gidapptools/data/gifs/__init__.py
gidapptools/data/gifs/busy_spinner_1.gif
gidapptools/data/gifs/busy_spinner_2.gif
gidapptools/data/gifs/busy_spinner_3.gif
gidapptools/data/gifs/busy_spinner_4.gif
gidapptools/data/gifs/busy_spinner_5.gif
gidapptools/data/gifs/busy_spinner_6.gif
gidapptools/data/gifs/busy_spinner_7.gif
gidapptools/data/gifs/busy_spinner_cat.gif
gidapptools/data/images/__init__.py
gidapptools/data/images/default_config_category_image.png
gidapptools/data/images/settings_default_icon.png
gidapptools/data/json/__init__.py
gidapptools/data/json/webcolors.json
gidapptools/data/py/__init__.py
gidapptools/general_helper/__init__.py
gidapptools/general_helper/ast_helper.py
gidapptools/general_helper/checker.py
gidapptools/general_helper/class_helper.py
gidapptools/general_helper/compress.py
gidapptools/general_helper/conversion.py
gidapptools/general_helper/date_time.py
gidapptools/general_helper/dict_helper.py
gidapptools/general_helper/dispatch_table.py
gidapptools/general_helper/enums.py
gidapptools/general_helper/general.py
gidapptools/general_helper/general_classes.py
gidapptools/general_helper/hashing.py
gidapptools/general_helper/import_helper.py
gidapptools/general_helper/io_helper.py
gidapptools/general_helper/path_helper.py
gidapptools/general_helper/ressource_classes.py
gidapptools/general_helper/string_helper.py
gidapptools/general_helper/timing.py
gidapptools/general_helper/typing_helper.py
gidapptools/general_helper/web_helper.py
gidapptools/general_helper/concurrency/__init__.py
gidapptools-0.8.8.dist-info/entry_points.txt
gidapptools-0.8.8.dist-info/licenses/LICENSE
gidapptools-0.8.8.dist-info/WHEEL
gidapptools-0.8.8.dist-info/METADATA
gidapptools-0.8.8.dist-info/RECORD
