Metadata-Version: 2.4
Name: gidapptools
Version: 0.8.8
Summary: WiP
Author: brocaprogs
Requires-Python: >=3.9
Classifier: License :: OSI Approved :: MIT License
License-File: LICENSE
Requires-Dist: attrs>=24.2.0
Requires-Dist: filelock>=3.15.4
Requires-Dist: frozendict>=2.4.4
Requires-Dist: orjson>=3.10.7
Requires-Dist: platformdirs>=4.2.2
Requires-Dist: portalocker>=3.1.1
Requires-Dist: psutil>=6.0
Requires-Dist: pyparsing>=3.1.4
Requires-Dist: python-dateutil>=1.16
Requires-Dist: pytz>=2024.1
Requires-Dist: tzlocal>=4.2
Requires-Dist: yarl>=1.15.0
Requires-Dist: PySide6>=6.8 ; extra == "all"
Requires-Dist: peewee>=3.15 ; extra == "all"
Requires-Dist: cython>=3.0.11 ; extra == "all"
Requires-Dist: rich>=13.1.1 ; extra == "all"
Requires-Dist: jinja2>=3.1.4 ; extra == "all"
Requires-Dist: apsw>=3.46.0.1 ; extra == "all"
Requires-Dist: Pillow>=10.4.0 ; extra == "all"
Requires-Dist: numpy>=2.0 ; extra == "all"
Requires-Dist: pyqtgraph>=0.13.7 ; extra == "all"
Requires-Dist: Pillow>=10.4.0 ; extra == "image"
Requires-Dist: numpy>=2.0 ; extra == "image"
Requires-Dist: peewee>=3.15 ; extra == "orm"
Requires-Dist: apsw>=3.46.1.0 ; extra == "orm"
Requires-Dist: PySide6>=6.8 ; extra == "pyside"
Requires-Dist: pyqtgraph>=0.13.7 ; extra == "pyside"
Requires-Dist: jinja2>=3.1.4 ; extra == "pyside"
Requires-Dist: rich>=13.7.1 ; extra == "rich"
Project-URL: Source, https://github.com/Giddius/GidAppTools
Provides-Extra: all
Provides-Extra: image
Provides-Extra: orm
Provides-Extra: parsing
Provides-Extra: pyside
Provides-Extra: rich
